{"performance-tests":{"500abf2bf8bcff4ce796ab791419645f99ac9f68":{"2020-01-04T14:57:52.430Z":[{"types":"no transformer","result":{"files":{"title":"Files","value":"187"},"lines":{"title":"Lines","value":"48011"},"nodes":{"title":"Nodes","value":"206582"},"identifiers":{"title":"Identifiers","value":"73444"},"symbols":{"title":"Symbols","value":"63251"},"types":{"title":"Types","value":"17674"},"memory_used":{"title":"Memory used","value":"135476K"},"i/o_read":{"title":"I/O read","value":"0.02"},"i/o_write":{"title":"I/O write","value":"0.01"},"parse_time":{"title":"Parse time","value":"0.93"},"bind_time":{"title":"Bind time","value":"0.55"},"check_time":{"title":"Check time","value":"2.07"},"emit_time":{"title":"Emit time","value":"0.15"},"total_time":{"title":"Total time","value":"3.70"}}}]},"163e48c5bd44513193e9dc8d0fc046ad94b7f7a8":{"2020-01-04T15:14:27.012Z":[{"types":"no transformer","result":{"files":{"title":"Files","value":"187"},"lines":{"title":"Lines","value":"48011"},"nodes":{"title":"Nodes","value":"206582"},"identifiers":{"title":"Identifiers","value":"73444"},"symbols":{"title":"Symbols","value":"63251"},"types":{"title":"Types","value":"17674"},"memory_used":{"title":"Memory used","value":"136361K"},"i/o_read":{"title":"I/O read","value":"0.02"},"i/o_write":{"title":"I/O write","value":"0.02"},"parse_time":{"title":"Parse time","value":"0.82"},"bind_time":{"title":"Bind time","value":"0.53"},"check_time":{"title":"Check time","value":"2.05"},"emit_time":{"title":"Emit time","value":"0.15"},"total_time":{"title":"Total time","value":"3.55"}}}]},"751e0e14bc635393a195ae5204665cb07a9fa4fe":{"2020-01-04T15:29:55.262Z":[{"types":"no transformer","result":{"files":{"title":"Files","value":"186"},"lines":{"title":"Lines","value":"47669"},"nodes":{"title":"Nodes","value":"205732"},"identifiers":{"title":"Identifiers","value":"73178"},"symbols":{"title":"Symbols","value":"63005"},"types":{"title":"Types","value":"17600"},"memory_used":{"title":"Memory used","value":"140009K"},"i/o_read":{"title":"I/O read","value":"0.03"},"i/o_write":{"title":"I/O write","value":"0.01"},"parse_time":{"title":"Parse time","value":"0.87"},"bind_time":{"title":"Bind time","value":"0.54"},"check_time":{"title":"Check time","value":"2.13"},"emit_time":{"title":"Emit time","value":"0.15"},"total_time":{"title":"Total time","value":"3.68"}}}]},"4a0b24e27d774e0097eaccb8894b5660ba7c15ec":{"2020-01-04T15:40:12.475Z":[{"types":"no transformer","result":{"files":{"title":"Files","value":"5086"},"lines":{"title":"Lines","value":"111369"},"nodes":{"title":"Nodes","value":"406632"},"identifiers":{"title":"Identifiers","value":"127078"},"symbols":{"title":"Symbols","value":"102205"},"types":{"title":"Types","value":"37200"},"memory_used":{"title":"Memory used","value":"401105K"},"i/o_read":{"title":"I/O read","value":"0.29"},"i/o_write":{"title":"I/O write","value":"0.45"},"parse_time":{"title":"Parse time","value":"1.87"},"bind_time":{"title":"Bind time","value":"0.89"},"check_time":{"title":"Check time","value":"4.66"},"emit_time":{"title":"Emit time","value":"3.62"},"total_time":{"title":"Total time","value":"11.04"}}},{"types":"no createMock","result":{"files":{"title":"Files","value":"5086"},"lines":{"title":"Lines","value":"111369"},"nodes":{"title":"Nodes","value":"406632"},"identifiers":{"title":"Identifiers","value":"127078"},"symbols":{"title":"Symbols","value":"102205"},"types":{"title":"Types","value":"37200"},"memory_used":{"title":"Memory used","value":"306666K"},"i/o_read":{"title":"I/O read","value":"0.30"},"i/o_write":{"title":"I/O write","value":"0.51"},"parse_time":{"title":"Parse time","value":"1.89"},"bind_time":{"title":"Bind time","value":"0.89"},"check_time":{"title":"Check time","value":"4.78"},"emit_time":{"title":"Emit time","value":"7.80"},"total_time":{"title":"Total time","value":"15.36"}}},{"types":"One interface per file","result":{"files":{"title":"Files","value":"5091"},"lines":{"title":"Lines","value":"111385"},"nodes":{"title":"Nodes","value":"436788"},"identifiers":{"title":"Identifiers","value":"137126"},"symbols":{"title":"Symbols","value":"102240"},"types":{"title":"Types","value":"32228"},"memory_used":{"title":"Memory used","value":"482068K"},"i/o_read":{"title":"I/O read","value":"0.36"},"i/o_write":{"title":"I/O write","value":"0.58"},"parse_time":{"title":"Parse time","value":"2.10"},"bind_time":{"title":"Bind time","value":"0.91"},"check_time":{"title":"Check time","value":"5.18"},"emit_time":{"title":"Emit time","value":"14.68"},"total_time":{"title":"Total time","value":"22.88"}}},{"types":"Interface reuse","result":{"files":{"title":"Files","value":"5091"},"lines":{"title":"Lines","value":"96385"},"nodes":{"title":"Nodes","value":"441788"},"identifiers":{"title":"Identifiers","value":"132126"},"symbols":{"title":"Symbols","value":"92241"},"types":{"title":"Types","value":"27228"},"memory_used":{"title":"Memory used","value":"382114K"},"i/o_read":{"title":"I/O read","value":"0.29"},"i/o_write":{"title":"I/O write","value":"0.54"},"parse_time":{"title":"Parse time","value":"2.11"},"bind_time":{"title":"Bind time","value":"0.93"},"check_time":{"title":"Check time","value":"5.02"},"emit_time":{"title":"Emit time","value":"11.74"},"total_time":{"title":"Total time","value":"19.80"}}},{"types":"One Interface / Reuse","result":{"files":{"title":"Files","value":"5091"},"lines":{"title":"Lines","value":"103885"},"nodes":{"title":"Nodes","value":"439288"},"identifiers":{"title":"Identifiers","value":"134626"},"symbols":{"title":"Symbols","value":"97241"},"types":{"title":"Types","value":"29728"},"memory_used":{"title":"Memory used","value":"451797K"},"i/o_read":{"title":"I/O read","value":"0.31"},"i/o_write":{"title":"I/O write","value":"0.56"},"parse_time":{"title":"Parse time","value":"2.20"},"bind_time":{"title":"Bind time","value":"0.91"},"check_time":{"title":"Check time","value":"5.11"},"emit_time":{"title":"Emit time","value":"13.53"},"total_time":{"title":"Total time","value":"21.75"}}}]},"f1cb2e9f6fe49a5608389f0518957cfd9b55dd5d":{"2020-01-04T16:07:29.150Z":[{"types":"no transformer","result":{"files":{"title":"Files","value":"5086"},"lines":{"title":"Lines","value":"111369"},"nodes":{"title":"Nodes","value":"406632"},"identifiers":{"title":"Identifiers","value":"127078"},"symbols":{"title":"Symbols","value":"102205"},"types":{"title":"Types","value":"37200"},"memory_used":{"title":"Memory used","value":"403268K"},"i/o_read":{"title":"I/O read","value":"0.26"},"i/o_write":{"title":"I/O write","value":"0.43"},"parse_time":{"title":"Parse time","value":"1.75"},"bind_time":{"title":"Bind time","value":"0.85"},"check_time":{"title":"Check time","value":"4.40"},"emit_time":{"title":"Emit time","value":"3.34"},"total_time":{"title":"Total time","value":"10.34"}}},{"types":"no createMock","result":{"files":{"title":"Files","value":"5086"},"lines":{"title":"Lines","value":"111369"},"nodes":{"title":"Nodes","value":"406632"},"identifiers":{"title":"Identifiers","value":"127078"},"symbols":{"title":"Symbols","value":"102205"},"types":{"title":"Types","value":"37200"},"memory_used":{"title":"Memory used","value":"306455K"},"i/o_read":{"title":"I/O read","value":"0.30"},"i/o_write":{"title":"I/O write","value":"0.46"},"parse_time":{"title":"Parse time","value":"1.73"},"bind_time":{"title":"Bind time","value":"0.92"},"check_time":{"title":"Check time","value":"4.40"},"emit_time":{"title":"Emit time","value":"7.36"},"total_time":{"title":"Total time","value":"14.41"}}},{"types":"One interface per file","result":{"files":{"title":"Files","value":"5091"},"lines":{"title":"Lines","value":"111385"},"nodes":{"title":"Nodes","value":"436788"},"identifiers":{"title":"Identifiers","value":"137126"},"symbols":{"title":"Symbols","value":"102240"},"types":{"title":"Types","value":"32228"},"memory_used":{"title":"Memory used","value":"480518K"},"i/o_read":{"title":"I/O read","value":"0.28"},"i/o_write":{"title":"I/O write","value":"0.57"},"parse_time":{"title":"Parse time","value":"1.97"},"bind_time":{"title":"Bind time","value":"0.96"},"check_time":{"title":"Check time","value":"4.89"},"emit_time":{"title":"Emit time","value":"14.13"},"total_time":{"title":"Total time","value":"21.96"}}},{"types":"Interface reuse","result":{"files":{"title":"Files","value":"5091"},"lines":{"title":"Lines","value":"96385"},"nodes":{"title":"Nodes","value":"441788"},"identifiers":{"title":"Identifiers","value":"132126"},"symbols":{"title":"Symbols","value":"92241"},"types":{"title":"Types","value":"27228"},"memory_used":{"title":"Memory used","value":"379997K"},"i/o_read":{"title":"I/O read","value":"0.28"},"i/o_write":{"title":"I/O write","value":"0.52"},"parse_time":{"title":"Parse time","value":"2.02"},"bind_time":{"title":"Bind time","value":"0.86"},"check_time":{"title":"Check time","value":"4.64"},"emit_time":{"title":"Emit time","value":"11.23"},"total_time":{"title":"Total time","value":"18.74"}}},{"types":"One Interface / Reuse","result":{"files":{"title":"Files","value":"5091"},"lines":{"title":"Lines","value":"103885"},"nodes":{"title":"Nodes","value":"439288"},"identifiers":{"title":"Identifiers","value":"134626"},"symbols":{"title":"Symbols","value":"97241"},"types":{"title":"Types","value":"29728"},"memory_used":{"title":"Memory used","value":"453238K"},"i/o_read":{"title":"I/O read","value":"0.27"},"i/o_write":{"title":"I/O write","value":"0.54"},"parse_time":{"title":"Parse time","value":"2.02"},"bind_time":{"title":"Bind time","value":"0.85"},"check_time":{"title":"Check time","value":"4.73"},"emit_time":{"title":"Emit time","value":"12.82"},"total_time":{"title":"Total time","value":"20.42"}}}]}}}